qldev/__init__.py
qldev/box/__init__.py
qldev/box/client.py
qldev/box/handler.py
qldev/box/message.py
qldev/box/model.py
qldev/device/__init__.py
qldev/device/base.py
qldev/device/handler.py
qldev/device/message.py
qldev/device/parser.py
qldev/network/__init__.py
qldev/network/tcp.py
qldev/network/udp.py
qldev/utils/__init__.py
qldev/utils/crcutils.py
qldev/utils/local.py
qldev/x7base/__init__.py
qldev/x7base/devinfo.py
qldev/x7base/model.py
qldev/x7base/x7parser.py
qldev/x7base/x7tcp.py
qldev/x7base/x7udp.py
qldev/x7base/x7utils.py
qldev-1.2.1.dist-info/METADATA
qldev-1.2.1.dist-info/WHEEL
qldev-1.2.1.dist-info/top_level.txt
qldev-1.2.1.dist-info/RECORD
