Metadata-Version: 2.1
Name: qldev
Version: 1.2.1
Summary: api for quanlan box since v1.2.5
Author: eegion
Author-email: hehuajun@eegion.com
Requires-Dist: loguru
Requires-Dist: numpy
